pf_reasoning_tool/__init__.py
pf_reasoning_tool/tools/__init__.py
pf_reasoning_tool/tools/hw_ai_search_lookup_with_embed.py
pf_reasoning_tool/tools/pii_redaction_tool.py
pf_reasoning_tool/tools/reasoning_tool_call.py
pf_reasoning_tool/tools/reasoning_vision_tool.py
pf_reasoning_tool/tools/utils.py
pf_reasoning_tool/tools/vision_llm_tool.py
pf_reasoning_tool/tools/__pycache__/__init__.cpython-310.pyc
pf_reasoning_tool/tools/__pycache__/reasoning_tool_call.cpython-310.pyc
pf_reasoning_tool/tools/__pycache__/reasoning_vision_tool.cpython-310.pyc
pf_reasoning_tool/tools/__pycache__/utils.cpython-310.pyc
pf_reasoning_tool/tools/__pycache__/vision_llm_tool.cpython-310.pyc
pf_reasoning_tool/yamls/hw_ai_search_lookup_with_embed.yaml
pf_reasoning_tool/yamls/pii_redaction_tool.yaml
pf_reasoning_tool/yamls/reasoning_tool_call.yaml
pf_reasoning_tool/yamls/reasoning_vision_tool.yaml
pf_reasoning_tool/yamls/vision_llm_tool.yaml
tests/__init__.py
tests/test_reasoning_tool_call.py
pf_reasoning_tool-0.5.15.dist-info/METADATA
pf_reasoning_tool-0.5.15.dist-info/WHEEL
pf_reasoning_tool-0.5.15.dist-info/entry_points.txt
pf_reasoning_tool-0.5.15.dist-info/top_level.txt
pf_reasoning_tool-0.5.15.dist-info/RECORD
