Metadata-Version: 2.4
Name: pf_reasoning_tool
Version: 0.5.15
Summary: Custom PromptFlow tools for Hall & Wilcox
Requires-Dist: promptflow-tools>=1.5.0
Requires-Dist: ruamel.yaml>=0.17
Requires-Dist: openai>=1.10.0
Requires-Dist: azure-ai-textanalytics==5.3.0
Requires-Dist: azure-search-documents==11.4.0
Requires-Dist: azure-identity
Dynamic: requires-dist
Dynamic: summary
